django_osm_field-0.6.0.dist-info/licenses/LICENSE
osm_field/__init__.py
osm_field/apps.py
osm_field/fields.py
osm_field/forms.py
osm_field/models.py
osm_field/validators.py
osm_field/widgets.py
osm_field/static/css/osm_field.css
osm_field/static/css/osm_field.min.css
osm_field/static/css/vendor/leaflet.css
osm_field/static/css/vendor/images/layers-2x.png
osm_field/static/css/vendor/images/layers.png
osm_field/static/js/osm_field.js
osm_field/static/js/osm_field.min.js
osm_field/static/js/vendor/jquery-3.5.0.min.js
osm_field/static/js/vendor/leaflet.js
osm_field/static/js/vendor/images/marker-icon-2x.png
osm_field/static/js/vendor/images/marker-icon.png
osm_field/static/js/vendor/images/marker-shadow.png
django_osm_field-0.6.0.dist-info/METADATA
django_osm_field-0.6.0.dist-info/WHEEL
django_osm_field-0.6.0.dist-info/top_level.txt
django_osm_field-0.6.0.dist-info/RECORD
