Metadata-Version: 2.4
Name: django-osm-field
Version: 0.6.0
Summary: Django OpenStreetMap Field
Author-email: Markus Holtermann <info@markusholtermann.eu>, Thomas Schmidt <schmidt@netaction.de>
License-Expression: MIT
Project-URL: Changelog, https://github.com/MarkusH/django-osm-field/blob/main/CHANGELOG.md
Project-URL: Funding, https://github.com/sponsors/MarkusH/
Project-URL: Repository, https://github.com/MarkusH/django-osm-field
Keywords: Django,Geo,Geoposition,OpenStreetMap,OSM
Classifier: Development Status :: 5 - Production/Stable
Classifier: Environment :: Web Environment
Classifier: Framework :: Django
Classifier: Framework :: Django :: 4.2
Classifier: Framework :: Django :: 5.0
Classifier: Framework :: Django :: 5.1
Classifier: Framework :: Django :: 5.2
Classifier: Framework :: Django :: 6.0
Classifier: Framework :: IPython
Classifier: Intended Audience :: Developers
Classifier: Natural Language :: English
Classifier: Operating System :: OS Independent
Classifier: Programming Language :: Python :: 3 :: Only
Classifier: Programming Language :: Python :: 3.9
Classifier: Programming Language :: Python :: 3.10
Classifier: Programming Language :: Python :: 3.11
Classifier: Programming Language :: Python :: 3.12
Classifier: Programming Language :: Python :: 3.13
Classifier: Programming Language :: Python :: 3.14
Classifier: Programming Language :: Python :: Implementation :: CPython
Classifier: Typing :: Typed
Requires-Python: >=3.9
License-File: LICENSE
Requires-Dist: django>=4.2
Dynamic: license-file
